{
  "@context": "http://iiif.io/api/presentation/3/context.json",
  "id": "https://xn--kleiderbgel-0hb.xn--blaufusstlpel-qmb.de/collection.json",
  "type": "Collection",
  "label": {
      "de": [
        "Kleiderbügel"
      ]},
  "items": [{
        "id": "https://xn--kleiderbgel-0hb.xn--blaufusstlpel-qmb.de/post/102/manifest.json",
        "type": "Manifest","thumbnail": [{
    "id": "https://xn--kleiderbgel-0hb.xn--blaufusstlpel-qmb.de/post/102/front_hu6946137960289069859.png",
    "format": "image/jpeg",
    "type":"Image",
    "height": 136,
    "width": 300
  },{
        "id": "https://xn--kleiderbgel-0hb.xn--blaufusstlpel-qmb.de/post/102/front.png",
        "format": "image/jpeg",
        "type":"Image",
        "height": 1730,
        "width": 3817,
        "service": [{
          "id":"https://xn--kleiderbgel-0hb.xn--blaufusstlpel-qmb.de/post/102/front",
          "type": "ImageService2",
          "profile":"level0"
        }]
      }],"label": {
          "de": [
            "Bremerhaven Ketelsen Cuxhaven"
          ]}
      },{
        "id": "https://xn--kleiderbgel-0hb.xn--blaufusstlpel-qmb.de/post/97/manifest.json",
        "type": "Manifest","thumbnail": [{
    "id": "https://xn--kleiderbgel-0hb.xn--blaufusstlpel-qmb.de/post/97/front_hu17852285953785872467.png",
    "format": "image/jpeg",
    "type":"Image",
    "height": 166,
    "width": 300
  },{
        "id": "https://xn--kleiderbgel-0hb.xn--blaufusstlpel-qmb.de/post/97/front.png",
        "format": "image/jpeg",
        "type":"Image",
        "height": 2161,
        "width": 3896,
        "service": [{
          "id":"https://xn--kleiderbgel-0hb.xn--blaufusstlpel-qmb.de/post/97/front",
          "type": "ImageService2",
          "profile":"level0"
        }]
      }],"label": {
          "de": [
            "Ketelsen Bremerhaven-Bürger 42"
          ]}
      }]
}