{"@context":"http://iiif.io/api/presentation/3/context.json","id":"https://xn--kleiderbgel-0hb.xn--blaufusstlpel-qmb.de/collection.json","items":[{"id":"https://xn--kleiderbgel-0hb.xn--blaufusstlpel-qmb.de/post/120/manifest.json","label":{"de":["„Herres - Eigentum„"]},"thumbnail":[{"format":"image/jpeg","height":136,"id":"https://xn--kleiderbgel-0hb.xn--blaufusstlpel-qmb.de/post/120/front_hu_3cfe25ec0c91377c.png","type":"Image","width":300},{"format":"image/jpeg","height":1769,"id":"https://xn--kleiderbgel-0hb.xn--blaufusstlpel-qmb.de/post/120/front/full/full/0/default.jpg","service":[{"id":"https://xn--kleiderbgel-0hb.xn--blaufusstlpel-qmb.de/post/120/front","profile":"level0","type":"ImageService2"}],"type":"Image","width":3911}],"type":"Manifest"},{"id":"https://xn--kleiderbgel-0hb.xn--blaufusstlpel-qmb.de/post/98/manifest.json","label":{"de":["BUND"]},"thumbnail":[{"format":"image/jpeg","height":145,"id":"https://xn--kleiderbgel-0hb.xn--blaufusstlpel-qmb.de/post/98/front_hu_c844939ef3f39cca.png","type":"Image","width":300},{"format":"image/jpeg","height":1844,"id":"https://xn--kleiderbgel-0hb.xn--blaufusstlpel-qmb.de/post/98/front/full/full/0/default.jpg","service":[{"id":"https://xn--kleiderbgel-0hb.xn--blaufusstlpel-qmb.de/post/98/front","profile":"level0","type":"ImageService2"}],"type":"Image","width":3822}],"type":"Manifest"},{"id":"https://xn--kleiderbgel-0hb.xn--blaufusstlpel-qmb.de/post/32/manifest.json","label":{"de":["Bundeseigentum"]},"thumbnail":[{"format":"image/jpeg","height":118,"id":"https://xn--kleiderbgel-0hb.xn--blaufusstlpel-qmb.de/post/32/front_hu_276ab30bf5c9d6e.png","type":"Image","width":300},{"format":"image/jpeg","height":1527,"id":"https://xn--kleiderbgel-0hb.xn--blaufusstlpel-qmb.de/post/32/front/full/full/0/default.jpg","service":[{"id":"https://xn--kleiderbgel-0hb.xn--blaufusstlpel-qmb.de/post/32/front","profile":"level0","type":"ImageService2"}],"type":"Image","width":3867}],"type":"Manifest"},{"id":"https://xn--kleiderbgel-0hb.xn--blaufusstlpel-qmb.de/post/17/manifest.json","label":{"de":["Bundesgrenzschutz"]},"thumbnail":[{"format":"image/jpeg","height":140,"id":"https://xn--kleiderbgel-0hb.xn--blaufusstlpel-qmb.de/post/17/front_hu_19b5bb7d428c17d4.png","type":"Image","width":300},{"format":"image/jpeg","height":1839,"id":"https://xn--kleiderbgel-0hb.xn--blaufusstlpel-qmb.de/post/17/front/full/full/0/default.jpg","service":[{"id":"https://xn--kleiderbgel-0hb.xn--blaufusstlpel-qmb.de/post/17/front","profile":"level0","type":"ImageService2"}],"type":"Image","width":3941}],"type":"Manifest"}],"label":{"de":["Kleiderbügel"],"en":["Kleiderbügel"]},"type":"Collection"}