{
    "@context": "http://iiif.io/api/presentation/3/context.json",
    "id": "https://xn--kleiderbgel-0hb.xn--blaufusstlpel-qmb.de/collection.json",
    "type": "Collection",
    "label": {
        "de": [
          "Kleiderb端gel"
        ],
          "en": [
            "Kleiderb端gel"
          ]
        },
    "items": [{
          "id": "https://xn--kleiderbgel-0hb.xn--blaufusstlpel-qmb.de/post/114/manifest.json",
          "type": "Manifest","thumbnail": [{
    "id": "https://xn--kleiderbgel-0hb.xn--blaufusstlpel-qmb.de/post/114/front_hu_a6e272a5274314e.png",
    "format": "image/jpeg",
    "type":"Image",
    "height": 133,
    "width": 300
  },{
        "id": "https://xn--kleiderbgel-0hb.xn--blaufusstlpel-qmb.de/post/114/front/full/full/0/default.jpg",
        "format": "image/jpeg",
        "type":"Image",
        "height": 1691,
        "width": 3810,
        "service": [{
          "id":"https://xn--kleiderbgel-0hb.xn--blaufusstlpel-qmb.de/post/114/front",
          "type": "ImageService2",
          "profile":"level0"
        }]
      }],"label": {
            "de": [
              "Bremerhaven Ketelsen Hafenstr. 76-80"
            ]}
        },{
          "id": "https://xn--kleiderbgel-0hb.xn--blaufusstlpel-qmb.de/post/102/manifest.json",
          "type": "Manifest","thumbnail": [{
    "id": "https://xn--kleiderbgel-0hb.xn--blaufusstlpel-qmb.de/post/102/front_hu_72f5125c102b02b.png",
    "format": "image/jpeg",
    "type":"Image",
    "height": 136,
    "width": 300
  },{
        "id": "https://xn--kleiderbgel-0hb.xn--blaufusstlpel-qmb.de/post/102/front/full/full/0/default.jpg",
        "format": "image/jpeg",
        "type":"Image",
        "height": 1730,
        "width": 3817,
        "service": [{
          "id":"https://xn--kleiderbgel-0hb.xn--blaufusstlpel-qmb.de/post/102/front",
          "type": "ImageService2",
          "profile":"level0"
        }]
      }],"label": {
            "de": [
              "Bremerhaven Ketelsen Cuxhaven"
            ]}
        },{
          "id": "https://xn--kleiderbgel-0hb.xn--blaufusstlpel-qmb.de/post/97/manifest.json",
          "type": "Manifest","thumbnail": [{
    "id": "https://xn--kleiderbgel-0hb.xn--blaufusstlpel-qmb.de/post/97/front_hu_66d77408b250bb85.png",
    "format": "image/jpeg",
    "type":"Image",
    "height": 166,
    "width": 300
  },{
        "id": "https://xn--kleiderbgel-0hb.xn--blaufusstlpel-qmb.de/post/97/front/full/full/0/default.jpg",
        "format": "image/jpeg",
        "type":"Image",
        "height": 2161,
        "width": 3896,
        "service": [{
          "id":"https://xn--kleiderbgel-0hb.xn--blaufusstlpel-qmb.de/post/97/front",
          "type": "ImageService2",
          "profile":"level0"
        }]
      }],"label": {
            "de": [
              "Ketelsen Bremerhaven-B端rger 42"
            ]}
        },{
          "id": "https://xn--kleiderbgel-0hb.xn--blaufusstlpel-qmb.de/post/87/manifest.json",
          "type": "Manifest","thumbnail": [{
    "id": "https://xn--kleiderbgel-0hb.xn--blaufusstlpel-qmb.de/post/87/front_hu_16c1e85fce38a39c.png",
    "format": "image/jpeg",
    "type":"Image",
    "height": 181,
    "width": 300
  },{
        "id": "https://xn--kleiderbgel-0hb.xn--blaufusstlpel-qmb.de/post/87/front/full/full/0/default.jpg",
        "format": "image/jpeg",
        "type":"Image",
        "height": 2321,
        "width": 3854,
        "service": [{
          "id":"https://xn--kleiderbgel-0hb.xn--blaufusstlpel-qmb.de/post/87/front",
          "type": "ImageService2",
          "profile":"level0"
        }]
      }],"label": {
            "de": [
              "Schl端sing mann + mode Bremerhaven-G."
            ]}
        },{
          "id": "https://xn--kleiderbgel-0hb.xn--blaufusstlpel-qmb.de/post/60/manifest.json",
          "type": "Manifest","thumbnail": [{
    "id": "https://xn--kleiderbgel-0hb.xn--blaufusstlpel-qmb.de/post/60/front_hu_ec9882b44e07638b.png",
    "format": "image/jpeg",
    "type":"Image",
    "height": 176,
    "width": 300
  },{
        "id": "https://xn--kleiderbgel-0hb.xn--blaufusstlpel-qmb.de/post/60/front/full/full/0/default.jpg",
        "format": "image/jpeg",
        "type":"Image",
        "height": 2212,
        "width": 3764,
        "service": [{
          "id":"https://xn--kleiderbgel-0hb.xn--blaufusstlpel-qmb.de/post/60/front",
          "type": "ImageService2",
          "profile":"level0"
        }]
      }],"label": {
            "de": [
              "Jordan"
            ]}
        }]
  }